{
  "id": "sanctorale.03-23",
  "kind": "sanctoral",
  "scope": "universal",
  "structure": "mass",
  "title": {
    "la": "S. Turibii de Mogrovejo, episcopi",
    "es": "Santo Toribio de Mogrovejo, obispo",
    "en-US": "Saint Turibius of Mogrovejo, bishop",
    "pt-BR": "São Turíbio de Mogrovejo, bispo",
    "it": "SAN TURIBIO DE MOGROVEJO, vescovo",
    "fr": "Saint Turibio de Mogrovejo, évêque",
    "de": "Hl. Turibio von Mogrovejo, Bischof"
  },
  "description": {
    "en-US": "Born in Spain around the year 1538, he studied law at Salamanca. Elected bishop of Lima in 1580, he set out for America. Burning with apostolic zeal, he frequently convened synods and councils, which greatly advanced the religious life of the whole region. He staunchly defended the rights of the Church, assiduously provided for the flock entrusted to him, often visiting it in person, and gave himself with great devotion to the care of the native peoples. He died in the year 1606.",
    "la": "Natus in Hispania circa annum 1538, ius didicit Salmanticæ. Episcopus Limæ electus anno 1580 Americam petiit. Apostolico zelo flagrans, sæpe celebravit synodos et concilia, quæ vitam religiosam totius regionis maxime promoverunt. Iura Ecclésiæ strenue defendit, gregi sibi commisso assidue providit, illum sæpe invisens, dum etiam pro autochthonibus maximas impendit curas. Mortuus est anno 1606.",
    "es": "Nació en España hacia el 1538, y estudió derecho en Salamanca. Nombrado obispo de Lima el año 1580, marchó a América. Lleno de celo apostólico, reunió numerosos sínodos y concilios que promovieron con mucho fruto la vida religiosa de todo el virreinato. Defendió con valentía los derechos de la Iglesia, con gran dedicación a su grey y preocupación, sobre todo, por la población autóctona. Murió el año 1606.",
    "pt-BR": "Turíbio (Mayorga, província de Leão, Espanha, por volta de 1538 - Lima, Peru, 23 de março de 1606), bispo de Lima, trabalhou sem trégua para formar os cristãos e o clero, criar novas comunidades e seminários, celebrar sínodos e concílios, impelido sempre pelo zelo missionário para fazer resplandecer o nome de Cristo naquelas imensas regiões.",
    "it": "Turibio Alfonso (Mayorga de Campos, Spagna, 18 novembre 1538 - Santiago de Miraflores de Saña, Perù, 23 marzo 1606) assunse la guida della vastissima arcidiocesi di Ciudad de los Reyes (attuale Lima, Perù), operando indefessamente per restaurare nel clero la disciplina ecclesiastica, alquanto rilassata, e per difendere con tutte le forze la dignità degli indigeni, inimicandosi i potenti dominatori spagnoli. Eresse ospedali per i poveri e il primo seminario dell’America Latina, intuendo l’importanza di una formazione secondo la cultura locale. Incarnò la figura evangelica del pastore nella dedizione amorevole al gregge e nel rispetto della cultura indigena.",
    "fr": "Nul plus que Turibio de Mogrovejo (1538-1606) n’a contribué à implanter l’Église en Amérique latine. Dès son arrivée à Lima comme archevêque il commença à pérégriner sans prendre de repos, fondant des séminaires, construisant des hôpitaux et des églises, tenant des synodes. Il allait toujours à pied, sans jamais se relâcher dans le jeûne et la prière.",
    "de": "Dieser Heilige wurde in Spanien im Jahr 1538 geboren und studierte Recht in Salamanca. Als gewählter Bischof von Lima siedelte er nach Amerika über, wo er mit großem apostolischem Eifer zahlreiche Synoden und Konzile versammelte und so das religiöse Leben voran brachte. Er verteidigte mit Mut und Entschlossenheit die Rechte der Kirche und kümmerte sich mit besonderer Hingabe um die Belange der einheimischen Bevölkerung. Er starb im Jahr 1606."
  },
  "color": "white",
  "rank": "optional-memorial",
  "cycleScheme": "fixed",
  "includeGloria": false,
  "collect": {
    "options": [
      {
        "body": {
          "lines": {
            "la": [
              [
                {
                  "type": "text",
                  "text": "Deus, qui Ecclésiam tuam beáti Turíbii epíscopi apostólicis curis zelóque veritátis auxísti,"
                }
              ],
              [
                {
                  "type": "text",
                  "text": "concéde, ut pópulus tibi sacrátus fídei et sanctitátis nova semper increménta suscípiat."
                }
              ],
              [
                {
                  "type": "text",
                  "text": "Per Dóminum."
                }
              ]
            ],
            "es": [
              [
                {
                  "type": "text",
                  "text": "Oh, Dios,"
                }
              ],
              [
                {
                  "type": "text",
                  "text": "que acrecentaste tu Iglesia mediante el celo por la verdad y la solicitud apostólica del obispo santo Toribio de Mogrovejo,"
                }
              ],
              [
                {
                  "type": "text",
                  "text": "concede al pueblo a ti consagrado crecer y renovárse continuamente en la fe y en la santidad."
                }
              ],
              [
                {
                  "type": "text",
                  "text": "Por nuestro Señor Jesucristo."
                }
              ]
            ],
            "en-US": [
              [
                {
                  "type": "text",
                  "text": "O God, who gave increase to your Church through the apostolic labors and zeal for truth of the Bishop Saint Turibius,"
                }
              ],
              [
                {
                  "type": "text",
                  "text": "grant that the people consecrated to you may always receive new growth in faith and holiness."
                }
              ],
              [
                {
                  "type": "text",
                  "text": "Through our Lord Jesus Christ, your Son,"
                }
              ],
              [
                {
                  "type": "text",
                  "text": "who lives and reigns with you in the unity of the Holy Spirit,"
                }
              ],
              [
                {
                  "type": "text",
                  "text": "one God, for ever and ever."
                }
              ]
            ],
            "pt-BR": [
              [
                {
                  "type": "text",
                  "text": "Ó Deus, que fizestes crescer a vossa Igreja pela solicitude pastoral do bispo São Turíbio e seu zelo pela verdade,"
                }
              ],
              [
                {
                  "type": "text",
                  "text": "concedei que o povo a vós consagrado cresça constantemente na fé e na santidade."
                }
              ],
              [
                {
                  "type": "text",
                  "text": "Por nosso Senhor Jesus Cristo, vosso Filho, que é Deus,"
                }
              ],
              [
                {
                  "type": "text",
                  "text": "e convosco vive e reina, na unidade do Espírito Santo,"
                }
              ],
              [
                {
                  "type": "text",
                  "text": "por todos os séculos dos séculos."
                }
              ]
            ],
            "it": [
              [
                {
                  "type": "text",
                  "text": "O Dio, che hai fatto crescere la tua Chiesa con le fatiche apostoliche e l’amore alla verità del vescovo san Turibio, concedi al popolo a te consacrato di crescere e rinnovarsi sempre nella fede e nella santità della vita. Per il nostro Signore Gesù Cristo, tuo Figlio, che è Dio, e vive e regna con te,"
                }
              ],
              [
                {
                  "type": "text",
                  "text": "nell’unità dello Spirito Santo, per tutti i secoli dei secoli."
                }
              ]
            ],
            "fr": [
              [
                {
                  "type": "text",
                  "text": "Seigneur Dieu,"
                }
              ],
              [
                {
                  "type": "text",
                  "text": "tu as fait grandir ton Église par les travaux apostoliques de l’évêque saint Turibio et par son amour de la vérité ;"
                }
              ],
              [
                {
                  "type": "text",
                  "text": "accorde au peuple qui t’est consacré une foi et une sainteté toujours en progrès."
                }
              ],
              [
                {
                  "type": "text",
                  "text": "Par Jésus Christ, ton Fils, notre Seigneur,"
                }
              ],
              [
                {
                  "type": "text",
                  "text": "qui vit et règne avec toi dans l’unité du Saint-Esprit,"
                }
              ],
              [
                {
                  "type": "text",
                  "text": "Dieu, pour les siècles des siècles."
                }
              ]
            ],
            "de": [
              [
                {
                  "type": "text",
                  "text": "Barmherziger Gott, durch die apostolische Arbeit des heiligen Bischofs Turibio und durch seinen Eifer für die wahre Lehre hast du in Lateinamerika die Kirche im Glauben gefestigt. Gib auch den Christen unserer Zeit neue Glaubenskraft und den Mut zu einem heiligen Leben. Darum bitten wir durch Jesus Christus."
                }
              ]
            ]
          }
        }
      }
    ]
  },
  "readings": {
    "default": {
      "firstReading": {
        "options": [
          {
            "label": {
              "la": "Lectio prior",
              "es": "Primera Lectura",
              "en-US": "First Reading",
              "pt-BR": "Primeira Leitura",
              "it": "Prima lettura",
              "fr": "Première lecture",
              "de": "Erste Lesung"
            },
            "citation": {
              "la": "2 Tim 1, 13-14; 2, 1-3",
              "es": "2 Tim 1, 13-14; 2, 1-3",
              "en-US": "2 Tim 1:13-14; 2:1-3",
              "pt-BR": "2 Tim 1, 13-14; 2, 1-3",
              "it": "2 Tm 1, 13-14; 2, 1-3",
              "fr": "2 Tm 1, 13-14; 2, 1-3",
              "de": "2 Tim 1, 13-14; 2, 1-3"
            },
            "introduction": {
              "la": "Léctio Epístolæ secúndæ beáti Pauli apóstoli ad Timótheum",
              "es": "Lectura de la segunda carta del apóstol san Pablo a Timoteo",
              "en-US": "A reading from the second letter of St. Paul to Timothy",
              "pt-BR": "Leitura da Segunda Carta de São Paulo a Timóteo",
              "it": "Dalla seconda lettera di san Paolo apostolo a Timoteo",
              "fr": "Deuxième lettre de saint Paul Apôtre à Timothée",
              "de": "Lesung aus dem zweiten Brief des Apostels Paulus an Timótheus"
            },
            "summary": {
              "la": "Bonum depositum custodi per Spíritum Sanctum.",
              "es": "Vela por el precioso depósito con la ayuda del Espíritu Santo",
              "pt-BR": "Guarda o precioso depósito, com a ajuda do Espírito Santo.",
              "it": "Custodisci, mediante lo Spirito Santo che abita in noi, il bene prezioso che ti è stato affidato."
            },
            "body": {
              "lines": {
                "la": [
                  [
                    {
                      "type": "text",
                      "text": "Caríssime: Formam habe sanórum verbórum, quæ a me audísti, in fide et dilectióne, quæ sunt in Christo Iesu; bonum depósitum custódi per Spíritum Sanctum, qui hábitat in nobis. Tu ergo, fili mi, confortáre in grátia, quæ est in Christo Iesu; et quæ audísti a me per multos testes, hæc comménda fidélibus homínibus, qui idónei erunt et álios docére. Collabóra sicut bonus miles Christi Iesu."
                    }
                  ]
                ],
                "es": [
                  [
                    {
                      "type": "text",
                      "text": "Querido hermano: Ten por modelo las palabras sanas que has oído de mí en la fe y el amor que tienen su fundamento en Cristo Jesús. Vela por el precioso depósito con la ayuda del Espíritu Santo que habita en nosotros. Así pues, tú, hijo mío, hazte fuerte en la gracia de Cristo Jesús, y lo que has oído de mí, a través de muchos testigos, esto mismo confíalo a hombres fieles, capaces, a su vez, de enseñar a otros. Toma parte en los padecimientos como buen soldado de Cristo Jesús."
                    }
                  ]
                ],
                "en-US": [
                  [
                    {
                      "type": "text",
                      "text": "Keep as your pattern the sound teaching you have heard from me, in the faith and love that are in Christ Jesus. You have been trusted to look after something precious; guard it with the help of the Holy Spirit who lives in us. Accept the strength, my dear son, that comes from the grace of Christ Jesus. You have heard everything that I teach in public; hand it on to reliable people so that they in turn will be able to teach others. Put up with your share of difficulties, like a good soldier of Christ Jesus."
                    }
                  ]
                ],
                "pt-BR": [
                  [
                    {
                      "type": "text",
                      "text": "Caríssimo: usa um compêndio das palavras sadias que de mim ouviste em matéria de fé e de amor em Cristo Jesus. Guarda o precioso depósito, com a ajuda do Espírito Santo que habita em nós. Meu filho, fortifica-te na graça de Jesus Cristo. O que de mim aprendeste na presença de tantas testemunhas, confia isso a homens fiéis, que sejam capazes de ensiná-lo também a outros. Assume a tua parte do sofrimento, como bom soldado de Cristo Jesus."
                    }
                  ]
                ],
                "it": [
                  [
                    {
                      "type": "text",
                      "text": "Figlio mio, prendi come modello i sani insegnamenti che hai udito da me con la fede e l’amore, che sono in Cristo Gesù. Custodisca, mediante lo Spirito Santo che abita in noi, il bene prezioso che ti è stato affidato. E tu, figlio mio, attingi forza dalla grazia che è in Cristo Gesù: le cose che hai udito da me davanti a molti testimoni, trasmettile a persone fidate, le quali a loro volta siano in grado di insegnare agli altri. Come un buon soldato di Gesù Cristo, soffri insieme con me."
                    }
                  ]
                ],
                "fr": [
                  [
                    {
                      "type": "text",
                      "text": "Caríssime : Bien-aimé, tiens-toi au modèle donné par les paroles solides que tu m’as entendu prononcer dans la foi et dans l’amour qui est dans le Christ Jésus. Garde le dépôt de la foi dans toute sa beauté, avec l’aide de l’Esprit Saint qui habite en nous. Toi donc, mon enfant, trouve ta force dans la grâce qui est en Jésus Christ. Ce que tu m’as entendu dire en présence de nombreux témoins, confie-le à des hommes dignes de foi qui seront capables de l’enseigner aux autres, à leur tour. Prends ta part de souffrance comme un bon soldat du Christ Jésus."
                    }
                  ]
                ],
                "de": [
                  [
                    {
                      "type": "text",
                      "text": "Mein Sohn! Halte dich an die gesunde Lehre, die du von mir gehört hast; nimm sie dir zum Vorbild, und bleibe beim Glauben und bei der Liebe, die uns in Christus Jesus geschenkt ist. Bewahre das dir anvertraute kostbare Gut durch die Kraft des Heiligen Geistes, der in uns wohnt. Du, mein Sohn, sei stark in der Gnade, die dir in Christus Jesus geschenkt ist. Was du vor vielen Zeugen von mir gehört hast, das vertrau zuverlässigen Menschen an, die fähig sind, auch andere zu lehren. Leide mit mir als guter Soldat Christi Jesu."
                    }
                  ]
                ]
              }
            },
            "conclusion": {
              "la": "Verbum Dómini.",
              "es": "Palabra de Dios.",
              "en-US": "The Word of the Lord.",
              "pt-BR": "Palavra do Senhor.",
              "it": "Parola di Dio.",
              "fr": "Parole du Seigneur.",
              "de": "Wort des lebendigen Gottes."
            }
          }
        ]
      },
      "gospel": {
        "options": [
          {
            "label": {
              "la": "Evangelium",
              "es": "Evangelio",
              "en-US": "Gospel",
              "pt-BR": "Evangelho",
              "it": "Vangelo",
              "fr": "Proclamation de l’Évangile",
              "de": "Evangelium"
            },
            "citation": {
              "la": "Mt 9, 35-38",
              "es": "Mt 9, 35-38",
              "en-US": "Mt 9:35-38",
              "pt-BR": "Mt 9, 35-38",
              "it": "Mt 9, 35-38",
              "fr": "Mt 9, 35-38",
              "de": "Mt 9, 35-38"
            },
            "introduction": {
              "la": "✠ Léctio sancti Evangélii secúndum Matthǽum",
              "es": "✠ Lectura del santo Evangelio según san Mateo",
              "en-US": "✠ A reading from the holy Gospel according to Matthew",
              "pt-BR": "✠ Proclamação do Evangelho de Jesus Cristo segundo Mateus",
              "it": "✠ Dal Vangelo secondo Matteo",
              "fr": "✠ Évangile de Jésus-Christ selon saint Matthieu",
              "de": "✠ Aus dem heiligen Evangelium nach Matthäus"
            },
            "summary": {
              "la": "Messis quidem multa, operarii autem pauci.",
              "es": "La mies es abundante, pero los trabajadores son pocos",
              "pt-BR": "A Messeé grande, mas os trabalhadores são poucos.",
              "it": "La messe è abbondante, ma sono pochi gli operai."
            },
            "body": {
              "lines": {
                "la": [
                  [
                    {
                      "type": "text",
                      "text": "In illo témpore: Circumíbat Iesus civitátes omnes et castélla, docens in synagógis eórum et prædicans Evangélium regni et curans omnem languórem et omnem infirmitátem. Videns autem turbas, misértus est eis, quia erant vexáti et iacéntes sicut oves non habéntes pastórem. Tunc dicit discípulis suis: «Messis quidem multa, operárii autem pauci; rogáte ergo Dóminum messis, ut mittat operários in messem suam»."
                    }
                  ]
                ],
                "es": [
                  [
                    {
                      "type": "text",
                      "text": "En aquel tiempo, Jesús recorría todas las ciudades y aldeas, enseñando en sus sinagogas, proclamando el evangelio del reino y curando toda enfermedad y toda dolencia. Al ver a las muchedumbres, se compadecía de ellas, porque estaban extenuadas y abandonadas, «como ovejas que no tienen pastor». Entonces dice a sus discípulos: «La mies es abundante, pero los trabajadores son pocos; rogad, pues, al Señor de la mies que mande trabajadores a su mies»."
                    }
                  ]
                ],
                "en-US": [
                  [
                    {
                      "type": "text",
                      "text": "Jesus made a tour through all the towns and villages, teaching in their synagogues, proclaiming the Good News of the kingdom and curing all kinds of diseases and sickness. 9:36And when he saw the crowds he felt sorry for them because they were harassed and dejected, like sheep without a shepherd. Then he said to his disciples, 'The harvest is rich but the labourers are few, so ask the Lord of the harvest to send labourers to his harvest'."
                    }
                  ]
                ],
                "pt-BR": [
                  [
                    {
                      "type": "text",
                      "text": "Naquele tempo, Jesus percorria todas as cidades e povoados, ensinando em suas sinagogas, pregando o Evangelho do Reino, e curando todo tipo de doença e enfermidade. Vendo Jesus as multidões, compadeceu-se delas, porque estavam cansadas e abatidas, como ovelhas que não têm pastor. Então disse a seus discípulos: \"A Messe é grande, mas os trabalhadores são poucos. Pedi pois ao dono da messe que envie trabalhadores para a sua colheita!\""
                    }
                  ]
                ],
                "it": [
                  [
                    {
                      "type": "text",
                      "text": "In quel tempo, Gesù percorreva tutte le città e i villaggi, insegnando nelle loro sinagoghe, annunciando il Vangelo del Regno e guarendo ogni malattia e ogni infermità. Vedendo le folle, ne sentì compassione, perché erano stanche e sfinite come pecore che non hanno pastore. Allora disse ai suoi discepoli: «La messe è abbondante, ma sono pochi gli operai! Pregate dunque il signore della messe, perché mandi operai nella sua messe!»."
                    }
                  ]
                ],
                "fr": [
                  [
                    {
                      "type": "text",
                      "text": "En ce temps-là, Jésus parcourait toutes les villes et tous les villages, enseignant dans leurs synagogues, proclamant l’Évangile du Royaume et guérissant toute maladie et toute infirmité. Voyant les foules, Jésus fut saisi de compassion envers elles parce qu’elles étaient désemparées et abattues comme des brebis sans berger. Il dit alors à ses disciples : « La moisson est abondante, mais les ouvriers sont peu nombreux. Priez donc le maître de la moisson d’envoyer des ouvriers pour sa moisson. »"
                    }
                  ]
                ],
                "de": [
                  [
                    {
                      "type": "text",
                      "text": "In jener Zeit zog Jesus durch alle Städte und Dörfer, lehrte in ihren Synagogen, verkündete das Evangelium vom Reich und heilte alle Krankheiten und Leiden. Als er die vielen Menschen sah, hatte er Mitleid mit ihnen; denn sie waren müde und erschöpft wie Schafe, die keinen Hirten haben. Da sagte er zu seinen Jüngern: Die Ernte ist groß, aber es gibt nur wenig Arbeiter. Bittet also den Herrn der Ernte, Arbeiter für seine Ernte auszusenden."
                    }
                  ]
                ]
              }
            },
            "conclusion": {
              "la": "Verbum Dómini.",
              "es": "Palabra del Señor.",
              "en-US": "The Gospel of the Lord.",
              "pt-BR": "Palavra da Salvação.",
              "it": "Parola del Signore.",
              "fr": "Acclamons la Parole de Dieu !",
              "de": "Evangelium unseres Herrn Jesus Christus."
            }
          }
        ]
      }
    }
  },
  "prefaces": [
    {
      "id": "pf056",
      "label": {
        "la": "PRÆFATIO DE SANCTIS PASTORIBUS",
        "es": "PREFACIO DE LOS SANTOS PASTORES",
        "en-US": "Preface of Holy Pastors",
        "pt-BR": "Prefácio dos Santos Pastores a",
        "it": "PREFAZIO DEI SANTI PASTORI I",
        "fr": "PRÉFACE DES SAINTS PASTEURS",
        "de": "PRÄFATION VON DEN HIRTEN DER KIRCHE"
      },
      "excerpt": {
        "la": "De præsentia sanctorum Pastorum in Ecclésia",
        "es": "La presencia de los santos pastores en la Iglesia",
        "en-US": "The presence of holy Pastors in the Church",
        "pt-BR": "presença dos Santos Pastores na Igreja",
        "it": "La presenza dei santi Pastori nella Chiesa",
        "fr": "La présence des saints pasteurs dans l’Église",
        "de": "Das Wirken der heiligen Hirten für uns"
      },
      "body": {
        "lines": {
          "la": [
            [
              {
                "type": "rubric",
                "text": "Sequens præfatio dicitur in sollemnitatibus et festis Ss. Pastorum. Dici potest in memoriis ipsorum."
              }
            ],
            [
              {
                "type": "text",
                "text": "Vere dignum et iustum est,"
              }
            ],
            [
              {
                "type": "text",
                "text": "æquum et salutáre,"
              }
            ],
            [
              {
                "type": "text",
                "text": "nos tibi semper et ubíque grátias ágere:"
              }
            ],
            [
              {
                "type": "text",
                "text": "Dómine, sancte Pater, omnípotens ætérne Deus:"
              }
            ],
            [
              {
                "type": "text",
                "text": "per Christum Dóminum nostrum."
              }
            ],
            [
              {
                "type": "text",
                "text": "Quia sic tríbuis Ecclésiam tuam sancti"
              }
            ],
            [
              {
                "type": "rubric",
                "text": "N."
              },
              {
                "type": "text",
                "text": "festivitáte gaudére,"
              }
            ],
            [
              {
                "type": "text",
                "text": "ut eam exémplo piæ conversatiónis corróbores,"
              }
            ],
            [
              {
                "type": "text",
                "text": "verbo prædicatiónis erúdias,"
              }
            ],
            [
              {
                "type": "text",
                "text": "gratáque tibi supplicatióne tueáris."
              }
            ],
            [
              {
                "type": "text",
                "text": "Et ídeo, cum Angelórum atque Sanctórum turba,"
              }
            ],
            [
              {
                "type": "text",
                "text": "hymnum laudis tibi cánimus, sine fine dicéntes:"
              }
            ]
          ],
          "es": [
            [
              {
                "type": "rubric",
                "text": "El siguiente prefacio se dice en las solemnidades y fiestas de los santos Pastores. Se puede decir también en las memorias de los mismos."
              }
            ],
            [
              {
                "type": "text",
                "text": "En verdad es justo y necesario,"
              }
            ],
            [
              {
                "type": "text",
                "text": "es nuestro deber y salvación darte gracias siempre y en todo lugar,"
              }
            ],
            [
              {
                "type": "text",
                "text": "Señor, Padre santo,"
              }
            ],
            [
              {
                "type": "text",
                "text": "Dios todopoderoso y eterno,"
              }
            ],
            [
              {
                "type": "text",
                "text": "por Cristo, Señor nuestro."
              }
            ],
            [
              {
                "type": "text",
                "text": "Porque nos concedes la alegría de celebrar hoy la fiesta de san"
              }
            ],
            [
              {
                "type": "rubric",
                "text": "N."
              }
            ],
            [
              {
                "type": "text",
                "text": ","
              }
            ],
            [
              {
                "type": "text",
                "text": "fortaleciendo a tu Iglesia con el ejemplo de su vida santa,"
              }
            ],
            [
              {
                "type": "text",
                "text": "instruyéndola con su palabra y protegiéndola con su intercesión."
              }
            ],
            [
              {
                "type": "text",
                "text": "Por eso,"
              }
            ],
            [
              {
                "type": "text",
                "text": "con los ángeles y con la multitud de los santos,"
              }
            ],
            [
              {
                "type": "text",
                "text": "te cantamos el himno de alabanza diciendo sin cesar:"
              }
            ]
          ],
          "en-US": [
            [
              {
                "type": "rubric",
                "text": "The following Preface is said on the Solemnities and Feasts of Holy Pastors. It may also be said on their Memorials."
              }
            ],
            [
              {
                "type": "text",
                "text": "It is truly right and just, our duty and our salvation,"
              }
            ],
            [
              {
                "type": "text",
                "text": "always and everywhere to give you thanks,"
              }
            ],
            [
              {
                "type": "text",
                "text": "Lord, holy Father, almighty and eternal God,"
              }
            ],
            [
              {
                "type": "text",
                "text": "through Christ our Lord."
              }
            ],
            [
              {
                "type": "text",
                "text": "For, as on the festival of Saint"
              },
              {
                "type": "rubric",
                "text": "N."
              },
              {
                "type": "text",
                "text": "you bid your Church rejoice,"
              }
            ],
            [
              {
                "type": "text",
                "text": "so, too, you strengthen her by the example of his holy life,"
              }
            ],
            [
              {
                "type": "text",
                "text": "teach her by his words of preaching,"
              }
            ],
            [
              {
                "type": "text",
                "text": "and keep her safe in answer to his prayers."
              }
            ],
            [
              {
                "type": "text",
                "text": "And so, with the company of Angels and Saints,"
              }
            ],
            [
              {
                "type": "text",
                "text": "we sing the hymn of your praise,"
              }
            ],
            [
              {
                "type": "text",
                "text": "as without end we acclaim:"
              }
            ]
          ],
          "pt-BR": [
            [
              {
                "type": "rubric",
                "text": "Este prefácio deve ser usado nas solenidades e festas dos Santos Pastores; ele pode ser rezado também em suas memórias."
              }
            ],
            [
              {
                "type": "text",
                "text": "Na verdade, é digno e justo,"
              }
            ],
            [
              {
                "type": "text",
                "text": "é nosso dever e salvação dar-vos graças,"
              }
            ],
            [
              {
                "type": "text",
                "text": "sempre e em todo lugar,"
              }
            ],
            [
              {
                "type": "text",
                "text": "Senhor, Pai santo,"
              }
            ],
            [
              {
                "type": "text",
                "text": "Deus eterno e todo-poderoso,"
              }
            ],
            [
              {
                "type": "text",
                "text": "por Cristo, Senhor nosso."
              }
            ],
            [
              {
                "type": "text",
                "text": "Vós nos concedeis a alegria de celebrar a memória"
              },
              {
                "type": "rubric",
                "text": "("
              },
              {
                "type": "text",
                "text": "festa, solenidade"
              },
              {
                "type": "rubric",
                "text": ")"
              },
              {
                "type": "text",
                "text": "de São"
              },
              {
                "type": "rubric",
                "text": "N."
              },
              {
                "type": "text",
                "text": "e fortaleceis a vossa Igreja com o exemplo de sua vida,"
              }
            ],
            [
              {
                "type": "text",
                "text": "o ensinamento de sua pregação e o auxílio de suas preces."
              }
            ],
            [
              {
                "type": "text",
                "text": "Por isso, com a multidão dos Anjos e dos Santos,"
              }
            ],
            [
              {
                "type": "text",
                "text": "entoamos o hino da vossa glória,"
              }
            ],
            [
              {
                "type": "text",
                "text": "cantando"
              },
              {
                "type": "rubric",
                "text": "("
              },
              {
                "type": "text",
                "text": "dizendo"
              },
              {
                "type": "rubric",
                "text": ")"
              },
              {
                "type": "text",
                "text": "a uma só voz:"
              }
            ]
          ],
          "it": [
            [
              {
                "type": "rubric",
                "text": "Il seguente prefazio si dice nelle solennità e nelle feste dei santi pastori. Si può dire anche nelle loro memorie."
              }
            ],
            [
              {
                "type": "text",
                "text": "È veramente cosa buona e giusta, nostro dovere e fonte di salvezza,"
              }
            ],
            [
              {
                "type": "text",
                "text": "rendere grazie sempre e in ogni luogo a te, Signore, Padre santo,"
              }
            ],
            [
              {
                "type": "text",
                "text": "Dio onnipotente ed eterno,"
              }
            ],
            [
              {
                "type": "text",
                "text": "per Cristo Signore nostro."
              }
            ],
            [
              {
                "type": "text",
                "text": "Tu doni alla tua Chiesa la gioia di celebrare la festa [memoria] di san N.:"
              }
            ],
            [
              {
                "type": "text",
                "text": "con i suoi esempi la rafforzi,"
              }
            ],
            [
              {
                "type": "text",
                "text": "con i suoi insegnamenti l’ammaestri,"
              }
            ],
            [
              {
                "type": "text",
                "text": "con la sua intercessione la proteggi."
              }
            ],
            [
              {
                "type": "text",
                "text": "Per questo dono della tua benevolenza,"
              }
            ],
            [
              {
                "type": "text",
                "text": "con la moltitudine degli angeli e dei santi,"
              }
            ],
            [
              {
                "type": "text",
                "text": "cantiamo senza fine l’inno della tua lode:"
              }
            ]
          ],
          "fr": [
            [
              {
                "type": "rubric",
                "text": "Cette Préface se dit pendant les solennités et les fêtes des saints Pasteurs. On peut aussi l’utiliser dans le cas d’une mémoire liturgique."
              }
            ],
            [
              {
                "type": "text",
                "text": "Vraiment, il est juste et bon,"
              }
            ],
            [
              {
                "type": "text",
                "text": "pour ta gloire et notre salut,"
              }
            ],
            [
              {
                "type": "text",
                "text": "de t’offrir notre action de grâce,"
              }
            ],
            [
              {
                "type": "text",
                "text": "toujours et en tout lieu,"
              }
            ],
            [
              {
                "type": "text",
                "text": "Seigneur, Père très saint,"
              }
            ],
            [
              {
                "type": "text",
                "text": "Dieu éternel et tout-puissant,"
              }
            ],
            [
              {
                "type": "text",
                "text": "par le Christ, notre Seigneur."
              }
            ],
            [
              {
                "type": "text",
                "text": "Tu donnes à ton Église de se réjouir en la fête de saint"
              },
              {
                "type": "rubric",
                "text": "("
              },
              {
                "type": "text",
                "text": "des saints"
              },
              {
                "type": "rubric",
                "text": ") N."
              },
              {
                "type": "text",
                "text": ":"
              }
            ],
            [
              {
                "type": "text",
                "text": "par l’exemple qu’il a"
              },
              {
                "type": "rubric",
                "text": "("
              },
              {
                "type": "text",
                "text": "qu’ils ont"
              },
              {
                "type": "rubric",
                "text": ")"
              },
              {
                "type": "text",
                "text": "donné, tu nous encourages,"
              }
            ],
            [
              {
                "type": "text",
                "text": "par son"
              },
              {
                "type": "rubric",
                "text": "("
              },
              {
                "type": "text",
                "text": "leur"
              },
              {
                "type": "rubric",
                "text": ")"
              },
              {
                "type": "text",
                "text": "enseignement, tu nous éclaires,"
              }
            ],
            [
              {
                "type": "text",
                "text": "à sa"
              },
              {
                "type": "rubric",
                "text": "("
              },
              {
                "type": "text",
                "text": "leur"
              },
              {
                "type": "rubric",
                "text": ")"
              },
              {
                "type": "text",
                "text": "prière, tu veilles sur nous."
              }
            ],
            [
              {
                "type": "text",
                "text": "C’est pourquoi,"
              }
            ],
            [
              {
                "type": "text",
                "text": "avec la multitude des anges et des saints,"
              }
            ],
            [
              {
                "type": "text",
                "text": "nous chantons l’hymne de ta gloire et sans fin nous proclamons :"
              }
            ]
          ],
          "de": [
            [
              {
                "type": "rubric",
                "text": "Diese Präfation wird an Hochfesten und Festen von Hirten der Kirche genommen."
              }
            ],
            [
              {
                "type": "text",
                "text": "In Wahrheit ist es würdig und recht, Dir, Vater im Himmel, zu danken und am Fest des heiligen"
              }
            ],
            [
              {
                "type": "rubric",
                "text": "N."
              },
              {
                "type": "text",
                "text": "deine Größe zu rühmen."
              }
            ],
            [
              {
                "type": "text",
                "text": "Sein Leben aus dem Glauben ist uns ein Vorbild, die Botschaft seiner Predigt belehrt uns, seine Fürbitte erwirkt uns Schutz und Hilfe durch unseren Herrn Jesus Christus."
              }
            ],
            [
              {
                "type": "text",
                "text": "Durch ihn preisen wir dich in deiner Kirche und vereinen uns mit den Engeln und Heiligen zum Hochgesang von deiner göttlichen Herrlichkeit:"
              }
            ]
          ]
        }
      }
    }
  ]
}
