{
  "id": "augustine-letters",
  "name": {
    "en-US": "Letters"
  },
  "author": {
    "en-US": "Augustine of Hippo"
  },
  "languages": [
    "en-US"
  ],
  "sources": [
    {
      "language": "en-US",
      "url": "http://www.newadvent.org/fathers/1102.htm",
      "description": "Translated by J.G. Cunningham. From Nicene and Post-Nicene Fathers, First Series, Vol. 1, Edited by Philip Schaff, Buffalo, NY: Christian Literature Publishing Co 1887. Revised and edited for New Advent by Kevin Knight."
    }
  ],
  "toc": [
    {
      "id": "ch001",
      "title": {
        "en-US": "Letter 1"
      }
    },
    {
      "id": "ch002",
      "title": {
        "en-US": "Letter 2"
      }
    },
    {
      "id": "ch003",
      "title": {
        "en-US": "Letter 3"
      }
    },
    {
      "id": "ch004",
      "title": {
        "en-US": "Letter 4"
      }
    },
    {
      "id": "ch005",
      "title": {
        "en-US": "Letter 5"
      }
    },
    {
      "id": "ch006",
      "title": {
        "en-US": "Letter 6"
      }
    },
    {
      "id": "ch007",
      "title": {
        "en-US": "Letter 7"
      }
    },
    {
      "id": "ch008",
      "title": {
        "en-US": "Letter 8"
      }
    },
    {
      "id": "ch009",
      "title": {
        "en-US": "Letter 9"
      }
    },
    {
      "id": "ch010",
      "title": {
        "en-US": "Letter 10"
      }
    },
    {
      "id": "ch011",
      "title": {
        "en-US": "Letter 11"
      }
    },
    {
      "id": "ch012",
      "title": {
        "en-US": "Letter 13"
      }
    },
    {
      "id": "ch013",
      "title": {
        "en-US": "Letter 14"
      }
    },
    {
      "id": "ch014",
      "title": {
        "en-US": "Letter 15"
      }
    },
    {
      "id": "ch015",
      "title": {
        "en-US": "Letter 16"
      }
    },
    {
      "id": "ch016",
      "title": {
        "en-US": "Letter 17"
      }
    },
    {
      "id": "ch017",
      "title": {
        "en-US": "Letter 18"
      }
    },
    {
      "id": "ch018",
      "title": {
        "en-US": "Letter 19"
      }
    },
    {
      "id": "ch019",
      "title": {
        "en-US": "Letter 20"
      }
    },
    {
      "id": "ch020",
      "title": {
        "en-US": "Letter 21"
      }
    },
    {
      "id": "ch021",
      "title": {
        "en-US": "Letter 22"
      }
    },
    {
      "id": "ch022",
      "title": {
        "en-US": "Letter 23"
      }
    },
    {
      "id": "ch023",
      "title": {
        "en-US": "Letter 25"
      }
    },
    {
      "id": "ch024",
      "title": {
        "en-US": "Letter 26"
      }
    },
    {
      "id": "ch025",
      "title": {
        "en-US": "Letter 27"
      }
    },
    {
      "id": "ch026",
      "title": {
        "en-US": "Letter 28"
      }
    },
    {
      "id": "ch027",
      "title": {
        "en-US": "Letter 29"
      }
    },
    {
      "id": "ch028",
      "title": {
        "en-US": "Letter 30"
      }
    },
    {
      "id": "ch029",
      "title": {
        "en-US": "Letter 31"
      }
    },
    {
      "id": "ch030",
      "title": {
        "en-US": "Letter 33"
      }
    },
    {
      "id": "ch031",
      "title": {
        "en-US": "Letter 34"
      }
    },
    {
      "id": "ch032",
      "title": {
        "en-US": "Letter 35"
      }
    },
    {
      "id": "ch033",
      "title": {
        "en-US": "Letter 36"
      }
    },
    {
      "id": "ch034",
      "title": {
        "en-US": "Letter 37"
      }
    },
    {
      "id": "ch035",
      "title": {
        "en-US": "Letter 38"
      }
    },
    {
      "id": "ch036",
      "title": {
        "en-US": "Letter 39"
      }
    },
    {
      "id": "ch037",
      "title": {
        "en-US": "Letter 40"
      }
    },
    {
      "id": "ch038",
      "title": {
        "en-US": "Letter 41"
      }
    },
    {
      "id": "ch039",
      "title": {
        "en-US": "Letter 42"
      }
    },
    {
      "id": "ch040",
      "title": {
        "en-US": "Letter 43"
      }
    },
    {
      "id": "ch041",
      "title": {
        "en-US": "Letter 44"
      }
    },
    {
      "id": "ch042",
      "title": {
        "en-US": "Letter 46"
      }
    },
    {
      "id": "ch043",
      "title": {
        "en-US": "Letter 47"
      }
    },
    {
      "id": "ch044",
      "title": {
        "en-US": "Letter 48"
      }
    },
    {
      "id": "ch045",
      "title": {
        "en-US": "Letter 50"
      }
    },
    {
      "id": "ch046",
      "title": {
        "en-US": "Letter 51"
      }
    },
    {
      "id": "ch047",
      "title": {
        "en-US": "Letter 53"
      }
    },
    {
      "id": "ch048",
      "title": {
        "en-US": "Letter 54"
      }
    },
    {
      "id": "ch049",
      "title": {
        "en-US": "Letter 55"
      }
    },
    {
      "id": "ch050",
      "title": {
        "en-US": "Letter 58"
      }
    },
    {
      "id": "ch051",
      "title": {
        "en-US": "Letter 59"
      }
    },
    {
      "id": "ch052",
      "title": {
        "en-US": "Letter 60"
      }
    },
    {
      "id": "ch053",
      "title": {
        "en-US": "Letter 61"
      }
    },
    {
      "id": "ch054",
      "title": {
        "en-US": "Letter 62"
      }
    },
    {
      "id": "ch055",
      "title": {
        "en-US": "Letter 63"
      }
    },
    {
      "id": "ch056",
      "title": {
        "en-US": "Letter 64"
      }
    },
    {
      "id": "ch057",
      "title": {
        "en-US": "Letter 65"
      }
    },
    {
      "id": "ch058",
      "title": {
        "en-US": "Letter 66"
      }
    },
    {
      "id": "ch059",
      "title": {
        "en-US": "Letter 67"
      }
    },
    {
      "id": "ch060",
      "title": {
        "en-US": "Letter 68"
      }
    },
    {
      "id": "ch061",
      "title": {
        "en-US": "Letter 69"
      }
    },
    {
      "id": "ch062",
      "title": {
        "en-US": "Letter 71"
      }
    },
    {
      "id": "ch063",
      "title": {
        "en-US": "Letter 72"
      }
    },
    {
      "id": "ch064",
      "title": {
        "en-US": "Letter 73"
      }
    },
    {
      "id": "ch065",
      "title": {
        "en-US": "Letter 74"
      }
    },
    {
      "id": "ch066",
      "title": {
        "en-US": "Letter 75"
      }
    },
    {
      "id": "ch067",
      "title": {
        "en-US": "Letter 76"
      }
    },
    {
      "id": "ch068",
      "title": {
        "en-US": "Letter 77"
      }
    },
    {
      "id": "ch069",
      "title": {
        "en-US": "Letter 78"
      }
    },
    {
      "id": "ch070",
      "title": {
        "en-US": "Letter 79"
      }
    },
    {
      "id": "ch071",
      "title": {
        "en-US": "Letter 81"
      }
    },
    {
      "id": "ch072",
      "title": {
        "en-US": "Letter 82"
      }
    },
    {
      "id": "ch073",
      "title": {
        "en-US": "Letter 83"
      }
    },
    {
      "id": "ch074",
      "title": {
        "en-US": "Letter 84"
      }
    },
    {
      "id": "ch075",
      "title": {
        "en-US": "Letter 85"
      }
    },
    {
      "id": "ch076",
      "title": {
        "en-US": "Letter 86"
      }
    },
    {
      "id": "ch077",
      "title": {
        "en-US": "Letter 87"
      }
    },
    {
      "id": "ch078",
      "title": {
        "en-US": "Letter 88"
      }
    },
    {
      "id": "ch079",
      "title": {
        "en-US": "Letter 89"
      }
    },
    {
      "id": "ch080",
      "title": {
        "en-US": "Letter 90"
      }
    },
    {
      "id": "ch081",
      "title": {
        "en-US": "Letter 91"
      }
    },
    {
      "id": "ch082",
      "title": {
        "en-US": "Letter 92"
      }
    },
    {
      "id": "ch083",
      "title": {
        "en-US": "Letter 93"
      }
    },
    {
      "id": "ch084",
      "title": {
        "en-US": "Letter 95"
      }
    },
    {
      "id": "ch085",
      "title": {
        "en-US": "Letter 96"
      }
    },
    {
      "id": "ch086",
      "title": {
        "en-US": "Letter 97"
      }
    },
    {
      "id": "ch087",
      "title": {
        "en-US": "Letter 98"
      }
    },
    {
      "id": "ch088",
      "title": {
        "en-US": "Letter 99"
      }
    },
    {
      "id": "ch089",
      "title": {
        "en-US": "Letter 100"
      }
    },
    {
      "id": "ch090",
      "title": {
        "en-US": "Letter 101"
      }
    },
    {
      "id": "ch091",
      "title": {
        "en-US": "Letter 102"
      }
    },
    {
      "id": "ch092",
      "title": {
        "en-US": "Letter 103"
      }
    },
    {
      "id": "ch093",
      "title": {
        "en-US": "Letter 104"
      }
    },
    {
      "id": "ch094",
      "title": {
        "en-US": "Letter 111"
      }
    },
    {
      "id": "ch095",
      "title": {
        "en-US": "Letter 115"
      }
    },
    {
      "id": "ch096",
      "title": {
        "en-US": "Letter 116"
      }
    },
    {
      "id": "ch097",
      "title": {
        "en-US": "Letter 117"
      }
    },
    {
      "id": "ch098",
      "title": {
        "en-US": "Letter 118"
      }
    },
    {
      "id": "ch099",
      "title": {
        "en-US": "Letter 122"
      }
    },
    {
      "id": "ch100",
      "title": {
        "en-US": "Letter 123"
      }
    },
    {
      "id": "ch101",
      "title": {
        "en-US": "Letter 124"
      }
    },
    {
      "id": "ch102",
      "title": {
        "en-US": "Letter 125"
      }
    },
    {
      "id": "ch103",
      "title": {
        "en-US": "Letter 126"
      }
    },
    {
      "id": "ch104",
      "title": {
        "en-US": "Letter 130"
      }
    },
    {
      "id": "ch105",
      "title": {
        "en-US": "Letter 131"
      }
    },
    {
      "id": "ch106",
      "title": {
        "en-US": "Letter 132"
      }
    },
    {
      "id": "ch107",
      "title": {
        "en-US": "Letter 133"
      }
    },
    {
      "id": "ch108",
      "title": {
        "en-US": "Letter 135"
      }
    },
    {
      "id": "ch109",
      "title": {
        "en-US": "Letter 136"
      }
    },
    {
      "id": "ch110",
      "title": {
        "en-US": "Letter 137"
      }
    },
    {
      "id": "ch111",
      "title": {
        "en-US": "Letter 138"
      }
    },
    {
      "id": "ch112",
      "title": {
        "en-US": "Letter 139"
      }
    },
    {
      "id": "ch113",
      "title": {
        "en-US": "Letter 143"
      }
    },
    {
      "id": "ch114",
      "title": {
        "en-US": "Letter 144"
      }
    },
    {
      "id": "ch115",
      "title": {
        "en-US": "Letter 145"
      }
    },
    {
      "id": "ch116",
      "title": {
        "en-US": "Letter 146"
      }
    },
    {
      "id": "ch117",
      "title": {
        "en-US": "Letter 148"
      }
    },
    {
      "id": "ch118",
      "title": {
        "en-US": "Letter 150"
      }
    },
    {
      "id": "ch119",
      "title": {
        "en-US": "Letter 151"
      }
    },
    {
      "id": "ch120",
      "title": {
        "en-US": "Letter 158"
      }
    },
    {
      "id": "ch121",
      "title": {
        "en-US": "Letter 159"
      }
    },
    {
      "id": "ch122",
      "title": {
        "en-US": "Letter 163"
      }
    },
    {
      "id": "ch123",
      "title": {
        "en-US": "Letter 164"
      }
    },
    {
      "id": "ch124",
      "title": {
        "en-US": "Letter 165"
      }
    },
    {
      "id": "ch125",
      "title": {
        "en-US": "Letter 166"
      }
    },
    {
      "id": "ch126",
      "title": {
        "en-US": "Letter 167"
      }
    },
    {
      "id": "ch127",
      "title": {
        "en-US": "Letter 169"
      }
    },
    {
      "id": "ch128",
      "title": {
        "en-US": "Letter 172"
      }
    },
    {
      "id": "ch129",
      "title": {
        "en-US": "Letter 173"
      }
    },
    {
      "id": "ch130",
      "title": {
        "en-US": "Letter 180"
      }
    },
    {
      "id": "ch131",
      "title": {
        "en-US": "Letter 185"
      }
    },
    {
      "id": "ch132",
      "title": {
        "en-US": "Letter 188"
      }
    },
    {
      "id": "ch133",
      "title": {
        "en-US": "Letter 189"
      }
    },
    {
      "id": "ch134",
      "title": {
        "en-US": "Letter 191"
      }
    },
    {
      "id": "ch135",
      "title": {
        "en-US": "Letter 192"
      }
    },
    {
      "id": "ch136",
      "title": {
        "en-US": "Letter 195"
      }
    },
    {
      "id": "ch137",
      "title": {
        "en-US": "Letter 201"
      }
    },
    {
      "id": "ch138",
      "title": {
        "en-US": "Letter 202"
      }
    },
    {
      "id": "ch139",
      "title": {
        "en-US": "Letter 203"
      }
    },
    {
      "id": "ch140",
      "title": {
        "en-US": "Letter 208"
      }
    },
    {
      "id": "ch141",
      "title": {
        "en-US": "Letter 209"
      }
    },
    {
      "id": "ch142",
      "title": {
        "en-US": "Letter 210"
      }
    },
    {
      "id": "ch143",
      "title": {
        "en-US": "Letter 211"
      }
    },
    {
      "id": "ch144",
      "title": {
        "en-US": "Letter 212"
      }
    },
    {
      "id": "ch145",
      "title": {
        "en-US": "Letter 213"
      }
    },
    {
      "id": "ch146",
      "title": {
        "en-US": "Letter 214"
      }
    },
    {
      "id": "ch147",
      "title": {
        "en-US": "Letter 215"
      }
    },
    {
      "id": "ch148",
      "title": {
        "en-US": "Letter 218"
      }
    },
    {
      "id": "ch149",
      "title": {
        "en-US": "Letter 219"
      }
    },
    {
      "id": "ch150",
      "title": {
        "en-US": "Letter 220"
      }
    },
    {
      "id": "ch151",
      "title": {
        "en-US": "Letter 227"
      }
    },
    {
      "id": "ch152",
      "title": {
        "en-US": "Letter 228"
      }
    },
    {
      "id": "ch153",
      "title": {
        "en-US": "Letter 229"
      }
    },
    {
      "id": "ch154",
      "title": {
        "en-US": "Letter 231"
      }
    },
    {
      "id": "ch155",
      "title": {
        "en-US": "Letter 232"
      }
    },
    {
      "id": "ch156",
      "title": {
        "en-US": "Letter 245"
      }
    },
    {
      "id": "ch157",
      "title": {
        "en-US": "Letter 246"
      }
    },
    {
      "id": "ch158",
      "title": {
        "en-US": "Letter 250"
      }
    },
    {
      "id": "ch159",
      "title": {
        "en-US": "Letter 254"
      }
    },
    {
      "id": "ch160",
      "title": {
        "en-US": "Letter 263"
      }
    },
    {
      "id": "ch161",
      "title": {
        "en-US": "Letter 269"
      }
    }
  ]
}
