{
 "sections": [
  {
   "name": "Officium",
   "lines": [
    "S. Petri Martyris",
    ""
   ]
  },
  {
   "name": "Rank",
   "lines": [
    ";;Duplex;;3;;vide C2a-1",
    "(sed rubrica 1617)",
    ";;Semiduplex;;2.2;;vide C2a-1",
    ""
   ]
  },
  {
   "name": "Rule",
   "lines": [
    "vide C2a-1;",
    ""
   ]
  },
  {
   "name": "Oratio",
   "lines": [
    "Præsta, quǽsumus, omnípotens Deus: ut beáti Petri Mártyris tui fidem cóngrua devotióne sectémur; qui, pro ejúsdem fídei dilatatióne, martýrii palmam méruit obtinére.",
    "$Per Dominum.",
    ""
   ]
  },
  {
   "name": "Lectio",
   "lines": [
    "@Commune/C2a-1",
    ""
   ]
  },
  {
   "name": "Secreta",
   "lines": [
    "Preces, quas tibi, Dómine, offérimus, intercedénte beáto Petro Mártyre tuo, cleménter inténde: et propugnatóres fídei sub tua protectióne custódi.",
    "$Per Dominum",
    ""
   ]
  },
  {
   "name": "Postcommunio",
   "lines": [
    "Fidéles tuos, Dómine, custódiant sacraménta, quæ súmpsimus: et, intercedénte beáto Petro Mártyre tuo, contra omnes advérsos tueántur incúrsus.",
    "$Per Dominum"
   ]
  }
 ]
}
